<?xml version="1.0" encoding="UTF-8"?>
<Document>
<TEXT>ICE-TD, <NODE id="8" />Sonntag, 17. April 2016<NODE id="31" />, <NODE id="33" />23:09<NODE id="38" /> (vor <NODE id="44" />3 Tagen<NODE id="51" />) @ Eisenbahnwilli
bearbeitet von ICE-TD, <NODE id="93" />Sonntag, 17. April 2016<NODE id="116" />, <NODE id="118" />23:10<NODE id="123" />
OT: Ich hatte mal eine Überholung im <NODE id="161" />RE 7<NODE id="165" /> in <NODE id="169" />Holzwickede<NODE id="180" /> Richtung <NODE id="190" />Hamm<NODE id="194" />, was ca. <NODE id="204" />7 Minuten<NODE id="213" /> zusätzlich Verspätung brachte- nur um dem ICE vielleicht <NODE id="271" />3 Minuten<NODE id="280" /> zu ersparen. Mein Anschluss war deshalb weg. In Fahrtichtung <NODE id="342" />Köln<NODE id="346" /> wäre eine Überholung absolut sinnvoll gewesen, aber in Richtung <NODE id="411" />Hamm<NODE id="415" /> nicht.
Wenn die <NODE id="432" />RE7<NODE id="435" /> bereits in <NODE id="447" />Holzwickede<NODE id="458" /> überholt wird muß sie schon fast <NODE id="492" />10 min<NODE id="498" /> gehabt haben vorher, wäre sie pünktlich gewesen hätte es gar keine Überholung gegeben. Hätte man den ICE dahinter gelassen wären das für den ICE mindestens <NODE id="655" />7-8 min<NODE id="662" /> Verspätung gewesen, diese hätte dieser dann dem <NODE id="711" />RE 6<NODE id="715" /> aufgedrückt und die Anschlüsse des ICE in <NODE id="758" />Hannover<NODE id="766" /> wären auch weg gewesen. Hättest du dann im deshalb verspäteten <NODE id="830" />RE6<NODE id="833" /> gesessen hättest du hier genauso gemeckert über den bösen Fernverkehr.

</TEXT>
<Meta>
<feature featureName="id" featureValue="http://www.ice-treff.de/index.php?id=414509@2016-04-17T23:09:42.000+02:00" />
<feature featureName="source" featureValue="news" />
<feature featureName="lang" featureValue="de" />
<feature featureName="pubDate" featureValue="2016-04-17T21:09:42Z" />
<feature featureName="indexDate" featureValue="2016-04-20T16:20:43.056Z" />
<feature featureName="uri" featureValue="http://www.ice-treff.de/index.php?id=414509" />
<feature featureName="solrEventType" featureValue="Verzoegerung" /></Meta><Entities>
<Entity id="0" startPos="8" endPos="31" type="date" surface="Sonntag, 17. April 2016" />
<Entity id="1" startPos="33" endPos="38" type="time" surface="23:09" />
<Entity id="2" startPos="44" endPos="51" type="date" surface="3 Tagen" />
<Entity id="3" startPos="93" endPos="116" type="date" surface="Sonntag, 17. April 2016" />
<Entity id="4" startPos="118" endPos="123" type="time" surface="23:10" />
<Entity id="5" startPos="161" endPos="165" type="location-route" surface="RE 7" />
<Entity id="6" startPos="169" endPos="180" type="location-stop" surface="Holzwickede" />
<Entity id="7" startPos="190" endPos="194" type="location-city" surface="Hamm" />
<Entity id="8" startPos="204" endPos="213" type="duration" surface="7 Minuten" />
<Entity id="9" startPos="271" endPos="280" type="duration" surface="3 Minuten" />
<Entity id="10" startPos="342" endPos="346" type="location-city" surface="Köln" />
<Entity id="11" startPos="411" endPos="415" type="location-city" surface="Hamm" />
<Entity id="12" startPos="432" endPos="435" type="location-route" surface="RE7" />
<Entity id="13" startPos="447" endPos="458" type="location-stop" surface="Holzwickede" />
<Entity id="14" startPos="492" endPos="498" type="duration" surface="10 min" />
<Entity id="15" startPos="655" endPos="662" type="duration" surface="7-8 min" />
<Entity id="16" startPos="711" endPos="715" type="location-route" surface="RE 6" />
<Entity id="17" startPos="758" endPos="766" type="location-stop" surface="Hannover" />
<Entity id="18" startPos="830" endPos="833" type="location-route" surface="RE6" /></Entities><Relations />
</Document>
