<?xml version="1.0" encoding="UTF-8"?>
<Document>
<TEXT><NODE id="0" />STARFACE<NODE id="8" /> launcht All-IP-Microsite und Beratungshotline
<NODE id="55" />Mo, 02/08/2016<NODE id="69" /> - <NODE id="72" />14:07<NODE id="77" />
Die <NODE id="82" />STARFACE GmbH<NODE id="95" /> ging am <NODE id="104" />5. Februar 2016<NODE id="119" /> mit der neuen All-IP-Microsite www.all-ip-umstellung.de online. Unternehmen finden dort praxisnahe Tipps und Informationen rund um die Migration von <NODE id="269" />ISDN<NODE id="273" /> auf All-IP. Parallel zum Start des Online-Portals stellt <NODE id="331" />STARFACE<NODE id="339" /> den von der <NODE id="352" />ISDN<NODE id="356" />-Abschaltung betroffenen Kunden mit dem All-IP Competence-Center zudem eine kostenlose Service-Hotline zur Verfügung.
Die All-IP-Umstellung ist eines der wichtigsten IT-Themen des neuen Jahres, betont <NODE id="557" />STARFACE<NODE id="565" /> <NODE id="566" />Produktmanager<NODE id="580" /> <NODE id="581" />Benedikt Kantus<NODE id="596" /> und ergänzt: <NODE id="610" />STARFACE<NODE id="618" /> bietet Unternehmen, die im Zuge der <NODE id="655" />ISDN<NODE id="659" />-Abschaltung auf All-IP umsteigen müssen, eine breite Palette maßgeschneiderter Lösungen. Dabei ist es ganz egal, ob sie ihre bestehende <NODE id="796" />ISDN<NODE id="800" />-Infrastruktur weiterbetreiben, in eine native All-IP-Telefonanlage investieren oder in die Cloud wechseln wollen: Mit unseren für die All-I
</TEXT>
<Meta>
<feature featureName="id" featureValue="http://www.pressaktuell.de/node/229697@2016-02-08T15:07:00.000+01:00" />
<feature featureName="source" featureValue="news" />
<feature featureName="lang" featureValue="de" />
<feature featureName="pubDate" featureValue="2016-02-08T14:07:00Z" />
<feature featureName="indexDate" featureValue="2016-03-24T03:28:02.953Z" />
<feature featureName="uri" featureValue="http://www.pressaktuell.de/node/229697" />
<feature featureName="solrEventType" featureValue="None" /></Meta><Entities>
<Entity id="0" startPos="0" endPos="8" type="organization-company" surface="STARFACE" />
<Entity id="1" startPos="55" endPos="69" type="date" surface="Mo, 02/08/2016" />
<Entity id="2" startPos="72" endPos="77" type="time" surface="14:07" />
<Entity id="3" startPos="82" endPos="95" type="organization-company" surface="STARFACE GmbH" />
<Entity id="4" startPos="104" endPos="119" type="date" surface="5. Februar 2016" />
<Entity id="5" startPos="269" endPos="273" type="product" surface="ISDN" />
<Entity id="6" startPos="331" endPos="339" type="organization-company" surface="STARFACE" />
<Entity id="7" startPos="352" endPos="356" type="product" surface="ISDN" />
<Entity id="8" startPos="557" endPos="565" type="organization-company" surface="STARFACE" />
<Entity id="9" startPos="566" endPos="580" type="org-position" surface="Produktmanager" />
<Entity id="10" startPos="581" endPos="596" type="person" surface="Benedikt Kantus" />
<Entity id="11" startPos="610" endPos="618" type="organization-company" surface="STARFACE" />
<Entity id="12" startPos="655" endPos="659" type="product" surface="ISDN" />
<Entity id="13" startPos="796" endPos="800" type="product" surface="ISDN" /></Entities><Relations />
</Document>
