<?xml version="1.0" encoding="UTF-8"?>
<Document>
<TEXT>Welcher <NODE id="8" />amerikanische<NODE id="21" /> Investor ist am vermögendsten?
Jetzt durchklicken
Wer hatte das größte Emissionsvolumen?
Jetzt durchklicken
Unternehmen, die unsere Welt verändert haben
Diese Top <NODE id="185" />20<NODE id="187" /> haben zur Verbessung der Welt beigetragen
Jetzt durchklicken
mehr Top Rankings
Umfrage
Die Wahlerfolge der rechtpopulistischen <NODE id="315" />AfD<NODE id="318" /> in <NODE id="322" />Baden-Württemberg<NODE id="339" />, <NODE id="341" />Rheinland-Pfalz<NODE id="356" /> und <NODE id="361" />Sachsen-Anhalt<NODE id="375" /> sind in der deutschen Wirtschaft mit gemischten Gefühlen und teils großer Sorge aufgenommen worden. Wie bewerten Sie diesen Erfolg?
Der Trend geht klar gegen <NODE id="534" />Europa<NODE id="540" /> und gegen den Euro.
Das war keine Wahl gegen <NODE id="586" />Europa<NODE id="592" />, sondern gegen die Flüchtlingspolitik von Kanzlerin Angela Merkel.
<NODE id="660" />AfD<NODE id="663" />-Wähler sind nicht alles Rechtsextremisten. Die Parteien müssen die Sorgen der Bürger ernst nehmen und zusammen an Lösungen arbeiten.
Abstimmen

</TEXT>
<Meta>
<feature featureName="id" featureValue="http://www.finanzen.net/nachricht/aktien/Entscheidung-zu-Fusion-von-Edeka-und-Tengelmann-Gabriel-Erklaerung-4785007@2016-03-17T09:32:46.000+01:00" />
<feature featureName="source" featureValue="news" />
<feature featureName="lang" featureValue="de" />
<feature featureName="pubDate" featureValue="2016-03-17T08:32:46Z" />
<feature featureName="indexDate" featureValue="2016-03-24T12:00:31.931Z" />
<feature featureName="uri" featureValue="http://www.finanzen.net/nachricht/aktien/Entscheidung-zu-Fusion-von-Edeka-und-Tengelmann-Gabriel-Erklaerung-4785007" />
<feature featureName="solrEventType" featureValue="Merger" /></Meta><Entities>
<Entity id="0" startPos="8" endPos="21" type="location" surface="amerikanische" />
<Entity id="1" startPos="185" endPos="187" type="number" surface="20" />
<Entity id="2" startPos="315" endPos="318" type="organization" surface="AfD" />
<Entity id="3" startPos="322" endPos="339" type="location" surface="Baden-Württemberg" />
<Entity id="4" startPos="341" endPos="356" type="location" surface="Rheinland-Pfalz" />
<Entity id="5" startPos="361" endPos="375" type="location" surface="Sachsen-Anhalt" />
<Entity id="6" startPos="534" endPos="540" type="location" surface="Europa" />
<Entity id="7" startPos="586" endPos="592" type="location" surface="Europa" />
<Entity id="8" startPos="660" endPos="663" type="organization" surface="AfD" /></Entities><Relations />
</Document>
