<?xml version="1.0" encoding="UTF-8"?>
<Document>
<TEXT>Die Zentrale der <NODE id="17" />Verbundnetz Gas AG<NODE id="35" /> (<NODE id="37" />VNG<NODE id="40" />) in <NODE id="45" />Leipzig<NODE id="52" /> ist zu sehen.
Foto: Jan Woitas/Archiv
Grünes Licht für Übernahme von <NODE id="122" />VNG<NODE id="125" />-Anteilen
erschienen am <NODE id="149" />17.03.2016<NODE id="159" />
<NODE id="160" />Karlsruhe<NODE id="169" />/<NODE id="170" />Leipzig<NODE id="177" /> (dpa/sn) - Internationale Behörden haben jetzt grünes Licht für die <NODE id="246" />Übernahme<NODE id="255" /> eines Großteils der Aktien der <NODE id="287" />Verbundnetz Gas AG<NODE id="305" /> (<NODE id="307" />VNG<NODE id="310" />/<NODE id="311" />Leipzig<NODE id="318" />) durch die <NODE id="330" />EnBW<NODE id="334" /> <NODE id="335" />Karlsruhe<NODE id="344" /> gegeben. Das Bundeskartellamt hatte der Transaktion bereits zugestimmt. Die Freigabe ähnlicher Behörden in <NODE id="452" />Österreich<NODE id="462" />, <NODE id="464" />Polen<NODE id="469" />, <NODE id="471" />Tschechien<NODE id="481" /> und der <NODE id="490" />Slowakei<NODE id="498" /> sei notwendig gewesen, weil <NODE id="527" />VNG<NODE id="530" /> dort tätig sei, teilte die <NODE id="558" />Energie-Baden-Württemberg AG<NODE id="586" /> am <NODE id="590" />Donnerstag<NODE id="600" /> in <NODE id="604" />Karlsruhe<NODE id="613" /> mit. <NODE id="619" />EnBW<NODE id="623" /> hatte im<NODE id="632" /> Oktober vorigen Jahres<NODE id="655" /> <NODE id="656" />74,2 Prozent<NODE id="668" /> der <NODE id="673" />VNG<NODE id="676" />-Aktien vom <NODE id="688" />Oldenburger<NODE id="699" /> Energieversorger <NODE id="717" />EWE<NODE id="720" /> <NODE id="721" />übernommen<NODE id="731" />. Die restlichen halten <NODE id="755" />ostdeutsche<NODE id="766" /> Kommunen.
<NODE id="777" />VNG<NODE id="780" /> war <NODE id="785" />2015<NODE id="789" /> tief in die roten Zahlen gerutscht. Der Fehlbetrag lag bei rund <NODE id="854" />53 Millionen Euro<NODE id="871" />. Der Umsatz ging von rund <NODE id="898" />10 Milliarden Euro<NODE id="916" /> im Jahr <NODE id="925" />2014<NODE id="929" /> auf <NODE id="934" />9,4 Milliarden Euro<NODE id="953" /> 
</TEXT>
<Meta>
<feature featureName="id" featureValue="http://www.freiepresse.de/NACHRICHTEN/SACHSEN/Gruenes-Licht-fuer-Uebernahme-von-VNG-Anteilen-artikel9465933.php@2016-03-17T11:55:19.000+01:00" />
<feature featureName="source" featureValue="news" />
<feature featureName="lang" featureValue="de" />
<feature featureName="uri" featureValue="http://www.freiepresse.de/NACHRICHTEN/SACHSEN/Gruenes-Licht-fuer-Uebernahme-von-VNG-Anteilen-artikel9465933.php" />
<feature featureName="solrEventType" featureValue="Übernahme" /></Meta><Entities>
<Entity id="0" startPos="17" endPos="35" type="organization-company" surface="Verbundnetz Gas AG" />
<Entity id="1" startPos="37" endPos="40" type="organization-company" surface="VNG" />
<Entity id="2" startPos="45" endPos="52" type="location-city" surface="Leipzig" />
<Entity id="3" startPos="122" endPos="125" type="organization-company" surface="VNG" />
<Entity id="4" startPos="149" endPos="159" type="date" surface="17.03.2016" />
<Entity id="5" startPos="160" endPos="169" type="location-city" surface="Karlsruhe" />
<Entity id="6" startPos="170" endPos="177" type="location-city" surface="Leipzig" />
<Entity id="7" startPos="246" endPos="255" type="trigger" surface="Übernahme" />
<Entity id="8" startPos="287" endPos="305" type="organization-company" surface="Verbundnetz Gas AG" />
<Entity id="9" startPos="307" endPos="310" type="organization-company" surface="VNG" />
<Entity id="10" startPos="311" endPos="318" type="location-city" surface="Leipzig" />
<Entity id="11" startPos="330" endPos="334" type="organization-company" surface="EnBW" />
<Entity id="12" startPos="335" endPos="344" type="location-city" surface="Karlsruhe" />
<Entity id="13" startPos="452" endPos="462" type="location" surface="Österreich" />
<Entity id="14" startPos="464" endPos="469" type="location" surface="Polen" />
<Entity id="15" startPos="471" endPos="481" type="location" surface="Tschechien" />
<Entity id="16" startPos="490" endPos="498" type="location" surface="Slowakei" />
<Entity id="17" startPos="527" endPos="530" type="organization-company" surface="VNG" />
<Entity id="18" startPos="558" endPos="586" type="organization-company" surface="Energie-Baden-Württemberg AG" />
<Entity id="19" startPos="590" endPos="600" type="date" surface="Donnerstag" />
<Entity id="20" startPos="604" endPos="613" type="location-city" surface="Karlsruhe" />
<Entity id="21" startPos="619" endPos="623" type="organization-company" surface="EnBW" />
<Entity id="22" startPos="632" endPos="655" type="date" surface=" Oktober vorigen Jahres" />
<Entity id="23" startPos="656" endPos="668" type="number" surface="74,2 Prozent" />
<Entity id="24" startPos="673" endPos="676" type="organization-company" surface="VNG" />
<Entity id="25" startPos="688" endPos="699" type="location-city" surface="Oldenburger" />
<Entity id="26" startPos="717" endPos="720" type="organization-company" surface="EWE" />
<Entity id="27" startPos="721" endPos="731" type="trigger" surface="übernommen" />
<Entity id="28" startPos="755" endPos="766" type="location" surface="ostdeutsche" />
<Entity id="29" startPos="777" endPos="780" type="organization-company" surface="VNG" />
<Entity id="30" startPos="785" endPos="789" type="date" surface="2015" />
<Entity id="31" startPos="854" endPos="871" type="number" surface="53 Millionen Euro" />
<Entity id="32" startPos="898" endPos="916" type="number" surface="10 Milliarden Euro" />
<Entity id="33" startPos="925" endPos="929" type="date" surface="2014" />
<Entity id="34" startPos="934" endPos="953" type="number" surface="9,4 Milliarden Euro" /></Entities><Relations>
<Relation id="35" NAME="Acquisition">
<Entity id="7" label="trigger" />
<Entity id="8" label="acquired" />
<Entity id="11" label="buyer" />
</Relation>
<Relation id="36" NAME="Acquisition">
<Entity id="22" label="date" />
<Entity id="26" label="seller" />
<Entity id="27" label="trigger" />
<Entity id="24" label="acquired" />
<Entity id="21" label="buyer" />
</Relation></Relations>
</Document>
