<?xml version="1.0" encoding="UTF-8"?>
<Document>
<TEXT><NODE id="0" />SwissSonic<NODE id="10" /> und <NODE id="15" />ProSeo-Consulting<NODE id="32" /> putten vom TV aufs Golfgrün
Ultraschall-Golfschlägerreiniger
[ Fotos ]
<NODE id="104" />Neustadt an der Weinstraße<NODE id="130" /> (pts021/<NODE id="139" />23.02.2016<NODE id="149" />/<NODE id="150" />13:30<NODE id="155" />) - Multichannel, crossmedial und personalisiert: Das sind die neuen Zaubermittel im Kampf und die Gunst des Verbrauchers. Da wirkt es wie ein Fairwayschlag direkt auf das Grün der schönen neuen Werbewelt für Anbieter mit Zielgruppe Golfer, dass der Pfälzer Vertrieb von crossmedialer Kommunikation rund um das Advertorial, <NODE id="479" />Proseo-Consulting GmbH<NODE id="501" />, mit dem <NODE id="511" />Speyerer<NODE id="519" /> Betreiber von Ultraschall-Golfschlägerreinigern, <NODE id="569" />SwissSonic GmbH<NODE id="584" />, <NODE id="586" />kooperiert<NODE id="596" />.
Reinigungsgerät wirbt für Reisemagazin
Golfer schauen gern das Golf-Tours-Reisemagazin - und zwar sind es laut Produzent der Sendung, askTV, <NODE id="739" />67 Prozent<NODE id="749" /> der rund <NODE id="759" />840 000<NODE id="766" /> Golfer in <NODE id="777" />Deutschland<NODE id="788" />. Die Reisesendung wird auf sky-Sport ausgestrahlt. Werbeeinspielungen und Platzierungen von Marken vor und im TV-Format Golf-Tours verknüpft der <NODE id="934" />Pfälzer<NODE id="941" /> Ver
</TEXT>
<Meta>
<feature featureName="id" featureValue="http://www.pressetext.com/news/20160223021@2016-02-23T13:30:00.000+01:00" />
<feature featureName="source" featureValue="news" />
<feature featureName="lang" featureValue="de" />
<feature featureName="pubDate" featureValue="2016-02-23T12:30:00Z" />
<feature featureName="indexDate" featureValue="2016-03-24T14:37:16.696Z" />
<feature featureName="uri" featureValue="http://www.pressetext.com/news/20160223021" />
<feature featureName="solrEventType" featureValue="None" /></Meta><Entities>
<Entity id="0" startPos="0" endPos="10" type="organization-company" surface="SwissSonic" />
<Entity id="1" startPos="15" endPos="32" type="organization-company" surface="ProSeo-Consulting" />
<Entity id="2" startPos="104" endPos="130" type="location-city" surface="Neustadt an der Weinstraße" />
<Entity id="3" startPos="139" endPos="149" type="date" surface="23.02.2016" />
<Entity id="4" startPos="150" endPos="155" type="date" surface="13:30" />
<Entity id="5" startPos="479" endPos="501" type="organization-company" surface="Proseo-Consulting GmbH" />
<Entity id="6" startPos="511" endPos="519" type="location-city" surface="Speyerer" />
<Entity id="7" startPos="569" endPos="584" type="organization-company" surface="SwissSonic GmbH" />
<Entity id="8" startPos="586" endPos="596" type="trigger" surface="kooperiert" />
<Entity id="9" startPos="739" endPos="749" type="number" surface="67 Prozent" />
<Entity id="10" startPos="759" endPos="766" type="number" surface="840 000" />
<Entity id="11" startPos="777" endPos="788" type="location" surface="Deutschland" />
<Entity id="12" startPos="934" endPos="941" type="location" surface="Pfälzer" /></Entities><Relations>
</Relations>
</Document>
