<?xml version="1.0" encoding="UTF-8"?>
<Document>
<TEXT><NODE id="0" />SPD<NODE id="3" /> weist Einmischung der Bezirksregierung zurück
<NODE id="50" />19.12.2015<NODE id="60" /> | <NODE id="63" />05:37 Uhr<NODE id="72" /> <NODE id="73" />2015-12-19<NODE id="83" />T<NODE id="84" />05:37:26+01:00<NODE id="98" />
Auf ziemliches Unverständnis bei <NODE id="132" />Duisburgs<NODE id="141" /> <NODE id="142" />SPD<NODE id="145" /> stößt die Einflussnahme der <NODE id="174" />Düsseldorfer<NODE id="186" /> Bezirksregierung bei der Frage der Neuordnung des Nahverkehrs und die von Regierungspräsidentin <NODE id="283" />Anne Lütkes<NODE id="294" /> gewünschte effizienteren Kooperation von <NODE id="336" />Duisburg<NODE id="344" />, <NODE id="346" />Mülheim<NODE id="353" /> und <NODE id="358" />Essen<NODE id="363" />.
Wie berichtet hat <NODE id="383" />Lütkes<NODE id="389" /> die <NODE id="394" />drei<NODE id="398" /> OB zum Rapport nach <NODE id="419" />Düsseldorf<NODE id="429" /> zitiert, nachdem <NODE id="447" />Duisburg<NODE id="455" /> ein Fusion in der gemeinsamen Verkehrsgesellschaft <NODE id="507" />Via<NODE id="510" /> abgelehnt hatte.
<NODE id="528" />SPD<NODE id="531" />-<NODE id="532" />Fraktions-Chef<NODE id="546" /> <NODE id="547" />Herbert Mettler<NODE id="562" /> zeigt sich überrascht über die Äußerungen von Regierungspräsidentin <NODE id="631" />Lütkes<NODE id="637" /> und erklärt im bissigen Unterton: „Ich vermute, Frau <NODE id="691" />Lütkes<NODE id="697" /> scheint im Fall der <NODE id="718" />Via<NODE id="721" /> nicht alle Fakten zu kennen. <NODE id="751" />Duisburg<NODE id="759" /> will sich nicht gänzlich aus der Verkehrsgemeinschaft <NODE id="814" />Via<NODE id="817" /> zurückziehen. Eine Fusion mit den Verkehrsgesellschaften aus <NODE id="879" />Essen<NODE id="884" /> und <NODE id="889" />Mülheim<NODE id="896" /> wird es jedoch nicht geben.“ Diese w
</TEXT>
<Meta>
<feature featureName="id" featureValue="http://www.derwesten.de/staedte/duisburg/spd-weist-einmischung-der-bezirksregierung-zurueck-aimp-id11394581.html@2015-12-19T05:57:27.000+01:00" />
<feature featureName="source" featureValue="news" />
<feature featureName="lang" featureValue="de" />
<feature featureName="pubDate" featureValue="2015-12-19T04:57:27Z" />
<feature featureName="indexDate" featureValue="2016-03-24T02:15:02.952Z" />
<feature featureName="uri" featureValue="http://www.derwesten.de/staedte/duisburg/spd-weist-einmischung-der-bezirksregierung-zurueck-aimp-id11394581.html" />
<feature featureName="solrEventType" featureValue="Insolvenz" /></Meta><Entities>
<Entity id="0" startPos="0" endPos="3" type="organization" surface="SPD" />
<Entity id="1" startPos="50" endPos="60" type="date" surface="19.12.2015" />
<Entity id="2" startPos="63" endPos="72" type="time" surface="05:37 Uhr" />
<Entity id="3" startPos="73" endPos="83" type="date" surface="2015-12-19" />
<Entity id="4" startPos="84" endPos="98" type="time" surface="05:37:26+01:00" />
<Entity id="5" startPos="132" endPos="141" type="location-city" surface="Duisburgs" />
<Entity id="6" startPos="142" endPos="145" type="organization" surface="SPD" />
<Entity id="7" startPos="174" endPos="186" type="location-city" surface="Düsseldorfer" />
<Entity id="8" startPos="283" endPos="294" type="person" surface="Anne Lütkes" />
<Entity id="9" startPos="336" endPos="344" type="location-city" surface="Duisburg" />
<Entity id="10" startPos="346" endPos="353" type="location-city" surface="Mülheim" />
<Entity id="11" startPos="358" endPos="363" type="location-city" surface="Essen" />
<Entity id="12" startPos="383" endPos="389" type="person" surface="Lütkes" />
<Entity id="13" startPos="394" endPos="398" type="number" surface="drei" />
<Entity id="14" startPos="419" endPos="429" type="location-city" surface="Düsseldorf" />
<Entity id="15" startPos="447" endPos="455" type="location-city" surface="Duisburg" />
<Entity id="16" startPos="507" endPos="510" type="organization" surface="Via" />
<Entity id="17" startPos="528" endPos="531" type="organization" surface="SPD" />
<Entity id="18" startPos="532" endPos="546" type="org-position" surface="Fraktions-Chef" />
<Entity id="19" startPos="547" endPos="562" type="person" surface="Herbert Mettler" />
<Entity id="20" startPos="631" endPos="637" type="person" surface="Lütkes" />
<Entity id="21" startPos="691" endPos="697" type="person" surface="Lütkes" />
<Entity id="22" startPos="718" endPos="721" type="organization" surface="Via" />
<Entity id="23" startPos="751" endPos="759" type="location-city" surface="Duisburg" />
<Entity id="24" startPos="814" endPos="817" type="organization" surface="Via" />
<Entity id="25" startPos="879" endPos="884" type="location-city" surface="Essen" />
<Entity id="26" startPos="889" endPos="896" type="location-city" surface="Mülheim" /></Entities><Relations>
<Relation id="27" NAME="OrganizationLeadership">
<Entity id="19" label="person" />
<Entity id="17" label="organization" />
<Entity id="18" label="position" />
</Relation></Relations>
</Document>
