<?xml version="1.0" encoding="UTF-8"?>
<Document>
<TEXT>Tiere
Verlorener Pottwalkadaver in der <NODE id="39" />Nordsee<NODE id="46" /> wiedergefunden
<NODE id="62" />Nordstrand<NODE id="72" /> (<NODE id="74" />dpa<NODE id="77" />) - In der <NODE id="88" />Nordsee<NODE id="95" /> hat der Küstenschutz den verloren gegangenen Pottwalkadaver wiedergefunden. Das tote Tier war bei einer Schleppaktion in der Nacht verloren gegangen. Man habe den Wal nahe der <NODE id="272" />Hallig Süderoog<NODE id="287" /> im Watt gesichtet, sagte ein Sprecher des <NODE id="330" />Landesbetriebes für Küstenschutz, Nationalpark und Meeresschutz<NODE id="393" />. Mit dem Hochwasser am Abend soll ein weiterer Versuch unternommen werden, das Tier in den Hafen in <NODE id="494" />Nordstrand<NODE id="504" /> zu schleppen. Der rund <NODE id="528" />zwölf Tonnen<NODE id="540" /> schwere Kadaver soll zerlegt werden.
Regionen

</TEXT>
<Meta>
<feature featureName="id" featureValue="http://www.gea.de/nachrichten/schlagzeilen/verlorener+pottwalkadaver+in+der+nordsee+wiedergefunden.4607290.htm?source=rss@2016-03-10T11:41:11.083+01:00" />
<feature featureName="source" featureValue="news" />
<feature featureName="lang" featureValue="de" />
<feature featureName="pubDate" featureValue="2016-03-10T10:41:11.083Z" />
<feature featureName="indexDate" featureValue="2016-03-10T10:41:11.49Z" />
<feature featureName="uri" featureValue="http://www.gea.de/nachrichten/schlagzeilen/verlorener+pottwalkadaver+in+der+nordsee+wiedergefunden.4607290.htm?source=rss" />
<feature featureName="solrEventType" featureValue="Naturereignis" /></Meta><Entities>
<Entity id="0" startPos="39" endPos="46" type="location" surface="Nordsee" />
<Entity id="1" startPos="62" endPos="72" type="location-city" surface="Nordstrand" />
<Entity id="2" startPos="74" endPos="77" type="organization-company" surface="dpa" />
<Entity id="3" startPos="88" endPos="95" type="location" surface="Nordsee" />
<Entity id="4" startPos="272" endPos="287" type="location" surface="Hallig Süderoog" />
<Entity id="5" startPos="330" endPos="393" type="organization" surface="Landesbetriebes für Küstenschutz, Nationalpark und Meeresschutz" />
<Entity id="6" startPos="494" endPos="504" type="location-city" surface="Nordstrand" />
<Entity id="7" startPos="528" endPos="540" type="number" surface="zwölf Tonnen" /></Entities><Relations />
</Document>
