<?xml version="1.0" encoding="UTF-8"?>
<Document>
<TEXT>RT @<NODE id="4" />faznet<NODE id="10" />: Der Panzerhersteller <NODE id="33" />Krauss-Maffei Wegmann<NODE id="54" /> besiegelt den <NODE id="69" />Zusammenschluss<NODE id="84" /> mit dem <NODE id="93" />französischen<NODE id="106" /> Rüstungskonzern <NODE id="123" />Nexter<NODE id="129" /> http://t.…
</TEXT>
<Meta>
<feature featureName="id" featureValue="626110721458352128" />
<feature featureName="source" featureValue="tweet" />
<feature featureName="lang" featureValue="de" />
<feature featureName="pubDate" featureValue="2015-07-28T19:23:23Z" />
<feature featureName="indexDate" featureValue="2016-03-12T01:19:05.728Z" />
<feature featureName="solrEventType" featureValue="Merger" /></Meta><Entities>
<Entity id="0" startPos="4" endPos="10" type="organization-company" surface="faznet" />
<Entity id="1" startPos="33" endPos="54" type="organization-company" surface="Krauss-Maffei Wegmann" />
<Entity id="2" startPos="69" endPos="84" type="trigger" surface="Zusammenschluss" />
<Entity id="3" startPos="93" endPos="106" type="location" surface="französischen" />
<Entity id="4" startPos="123" endPos="129" type="organization-company" surface="Nexter" /></Entities><Relations>
<Relation id="5" NAME="Merger">
<Entity id="4" label="old" />
<Entity id="1" label="old" />
<Entity id="2" label="trigger" />
</Relation></Relations>
</Document>
